dulwich/client.py
dulwich/config.py
dulwich/diff_tree.py
dulwich/errors.py
dulwich/fastexport.py
dulwich/file.py
dulwich/greenthreads.py
dulwich/hooks.py
dulwich/index.py
dulwich/log_utils.py
dulwich/lru_cache.py
dulwich/objects.py
dulwich/objectspec.py
dulwich/object_store.py
dulwich/pack.py
dulwich/patch.py
dulwich/porcelain.py
dulwich/protocol.py
dulwich/refs.py
dulwich/repo.py
dulwich/server.py
dulwich/stdint.h
dulwich/walk.py
dulwich/web.py
dulwich/_compat.py
dulwich/_diff_tree.c
dulwich/_diff_tree.pyd
dulwich/_objects.c
dulwich/_objects.pyd
dulwich/_pack.c
dulwich/_pack.pyd
dulwich/__init__.py
dulwich/contrib/swift.py
dulwich/contrib/test_swift.py
dulwich/contrib/test_swift_smoke.py
dulwich/contrib/__init__.py
dulwich/tests/test_blackbox.py
dulwich/tests/test_client.py
dulwich/tests/test_config.py
dulwich/tests/test_diff_tree.py
dulwich/tests/test_fastexport.py
dulwich/tests/test_file.py
dulwich/tests/test_grafts.py
dulwich/tests/test_greenthreads.py
dulwich/tests/test_hooks.py
dulwich/tests/test_index.py
dulwich/tests/test_lru_cache.py
dulwich/tests/test_missing_obj_finder.py
dulwich/tests/test_objects.py
dulwich/tests/test_objectspec.py
dulwich/tests/test_object_store.py
dulwich/tests/test_pack.py
dulwich/tests/test_patch.py
dulwich/tests/test_porcelain.py
dulwich/tests/test_protocol.py
dulwich/tests/test_refs.py
dulwich/tests/test_repository.py
dulwich/tests/test_server.py
dulwich/tests/test_utils.py
dulwich/tests/test_walk.py
dulwich/tests/test_web.py
dulwich/tests/utils.py
dulwich/tests/__init__.py
dulwich/tests/compat/server_utils.py
dulwich/tests/compat/test_client.py
dulwich/tests/compat/test_pack.py
dulwich/tests/compat/test_repository.py
dulwich/tests/compat/test_server.py
dulwich/tests/compat/test_utils.py
dulwich/tests/compat/test_web.py
dulwich/tests/compat/utils.py
dulwich/tests/compat/__init__.py
dulwich/tests/data/blobs/11/11111111111111111111111111111111111111
dulwich_windows-0.9.8.dist-info/DESCRIPTION.rst
dulwich_windows-0.9.8.dist-info/METADATA
dulwich_windows-0.9.8.dist-info/metadata.json
dulwich_windows-0.9.8.dist-info/RECORD
dulwich_windows-0.9.8.dist-info/top_level.txt
dulwich_windows-0.9.8.dist-info/WHEEL
